Quizzer/__init__.py
Quizzer/__main__.py
Quizzer/db_quizzes/english-speaking-small-talk_quiz.json
Quizzer/db_quizzes/english-speaking-weather-vocabulary-quiz.json
Quizzer/db_quizzes/english-vocabulary-animal-terms-quiz.json
Quizzer/db_quizzes/english-vocabulary-collocations-quiz-time.json
Quizzer/db_quizzes/english-vocabulary-computer-quiz.json
Quizzer/db_quizzes/english-vocabulary-criminals-quiz.json
Quizzer/db_quizzes/english-vocabulary-family-quiz.json
Quizzer/db_quizzes/english-vocabulary-festivals-christmas-quiz.json
Quizzer/db_quizzes/english-vocabulary-nsew-quiz.json
Quizzer/db_quizzes/english-vocabulary-numbers-quiz.json
Quizzer/db_quizzes/english-vocabulary-time-quiz.json
Quizzer/db_quizzes/english-vocabulary-weather-vocabulary-quiz.json
Quizzer/db_quizzes/english-vocabulary-world-countries-nationality-quiz.json
Quizzer/db_results/.gitkeep
Quizzer/quizuiflowcontrol/__init__.py
Quizzer/quizuiflowcontrol/main_menu.py
Quizzer/quizuiflowcontrol/quizmanager.py
Quizzer/quizutils/__init__.py
Quizzer/quizutils/quiz.py
Quizzer/quizutils/quizparser.py
QuizzerApp-0.0.3.dist-info/LICENSE.txt
QuizzerApp-0.0.3.dist-info/METADATA
QuizzerApp-0.0.3.dist-info/WHEEL
QuizzerApp-0.0.3.dist-info/top_level.txt
QuizzerApp-0.0.3.dist-info/RECORD
