Metadata-Version: 2.1
Name: QuizzerApp
Version: 0.0.3
Summary: This package helps you manage taking quizzes
Author-email: Nijiat Abulizi <nijiati.abulizi@gmail.com>, Kulaphong Jitareerat <kulapong.j@gmail.com>
Project-URL: Homepage, https://github.com/Nijat27/Quizzer
Project-URL: Issues, https://github.com/Nijat27/Quizzer/issues
Classifier: Programming Language :: Python :: 3
Classifier: License :: OSI Approved :: MIT License
Classifier: Operating System :: OS Independent
Requires-Python: >=3.9
License-File: LICENSE.txt
